metasheet/__init__.py
metasheet/__main__.py
metasheet/csv_to_sql.py
metasheet/metasheet.py
metasheet/sas_to_csv.py
metasheet/util/__init__.py
metasheet/util/classes.py
metasheet/util/config.json
metasheet/util/excel.py
metasheet/util/repository.py
metasheet/util/serializers/__init__.py
metasheet/util/serializers/bq.py
metasheet/util/serializers/ddi.py
metasheet/util/serializers/mockaroo.py
metasheet/util/serializers/mysql.py
metasheet/util/serializers/py.py
metasheet/util/serializers/rds.py
metasheet/util/serializers/rml.py
metasheet/util/serializers/sts.py
metasheet/util/serializers/vertica.py
mtna_metasheet-0.1.1.dist-info/LICENSE
mtna_metasheet-0.1.1.dist-info/METADATA
mtna_metasheet-0.1.1.dist-info/WHEEL
mtna_metasheet-0.1.1.dist-info/entry_points.txt
mtna_metasheet-0.1.1.dist-info/top_level.txt
mtna_metasheet-0.1.1.dist-info/RECORD
