Metadata-Version: 2.1
Name: mtna-metasheet
Version: 0.1.1
Summary: Metasheet parser, serializers, and repository manager
Home-page: UNKNOWN
Author: Pascal Heus
Author-email: pacsal.heus@mtna.us
License: UNKNOWN
Platform: UNKNOWN
Classifier: Development Status :: 4 - Beta
Classifier: Intended Audience :: Developers
Classifier: License :: OSI Approved :: MIT License
Classifier: Programming Language :: Python :: 3
Requires-Python: >=3.0
